tire_cpd/__init__.py
tire_cpd/functions/__init__.py
tire_cpd/functions/cpd.py
tire_cpd/functions/metrics.py
tire_cpd/functions/postprocessing.py
tire_cpd/functions/preprocessing.py
tire_cpd/functions/utils.py
tire_cpd/models/__init__.py
tire_cpd/models/diamond.py
tire_cpd/models/multichannel.py
tire_cpd/models/multiview.py
tire_cpd-0.1.3.dist-info/METADATA
tire_cpd-0.1.3.dist-info/WHEEL
tire_cpd-0.1.3.dist-info/RECORD
