Metadata-Version: 2.1
Name: tire-cpd
Version: 0.1.3
Summary: This is an unsupervised change point detection toolbox, including time-invariant representation (TIRE) model with diamond loss, multi-channel time-invariant representation (MC-TIRE) model, and multi-view time-invariant representation (multiview TIRE) model.
License: MIT
Author: Zhenxiang Cao
Requires-Python: >=3.10,<4.0
Classifier: License :: OSI Approved :: MIT License
Classifier: Programming Language :: Python :: 3
Classifier: Programming Language :: Python :: 3.10
Classifier: Programming Language :: Python :: 3.11
Classifier: Programming Language :: Python :: 3.12
Classifier: Programming Language :: Python :: 3.13
Requires-Dist: matplotlib (==3.7.4)
Requires-Dist: numpy (==1.23.5)
Requires-Dist: pandas (==2.1.1)
Requires-Dist: scikit-learn (==1.4.2)
Requires-Dist: scipy (==1.10.1)
Requires-Dist: seaborn (==0.12.2)
Requires-Dist: tensorflow (==2.12.0)
Requires-Dist: tensorflow-probability (==0.20.0)
